webcam_streamer-1.0.5.dist-info/DESCRIPTION.rst
webcam_streamer-1.0.5.dist-info/entry_points.txt
webcam_streamer-1.0.5.dist-info/METADATA
webcam_streamer-1.0.5.dist-info/metadata.json
webcam_streamer-1.0.5.dist-info/RECORD
webcam_streamer-1.0.5.dist-info/top_level.txt
webcam_streamer-1.0.5.dist-info/WHEEL
webcamstreamer/.DS_Store
webcamstreamer/__init__.py
webcamstreamer/__init__.pyc
webcamstreamer/launcher.py
webcamstreamer/launcher.pyc
webcamstreamer/streamer/__init__.py
webcamstreamer/streamer/__init__.pyc
webcamstreamer/streamer/camera.py
webcamstreamer/streamer/camera.pyc
webcamstreamer/streamer/camera_mock.py
webcamstreamer/streamer/camera_mock.pyc
webcamstreamer/streamer/defaults.py
webcamstreamer/streamer/defaults.pyc
webcamstreamer/streamer/static/app.js
webcamstreamer/streamer/static/skeleton.css
webcamstreamer/streamer/static/socketio.js
webcamstreamer/streamer/static/style.css
webcamstreamer/streamer/templates/index.html
