Metadata-Version: 2.0
Name: webcam-streamer
Version: 1.0.5
Summary: Simple USB webcam streaming
Home-page: https://github.com/theopolisme/webcam-streamer
Author: Theo Patt
Author-email: theo@theopatt.com
License: MIT
Keywords: usb webcam streaming
Platform: UNKNOWN
Classifier: Development Status :: 3 - Alpha
Classifier: Topic :: Multimedia :: Video
Classifier: License :: OSI Approved :: MIT License
Classifier: Programming Language :: Python :: 2
Classifier: Programming Language :: Python :: 2.6
Classifier: Programming Language :: Python :: 2.7
Classifier: Programming Language :: Python :: 3
Classifier: Programming Language :: Python :: 3.2
Classifier: Programming Language :: Python :: 3.3
Classifier: Programming Language :: Python :: 3.4
Requires-Dist: Flask (>=0.10)
Requires-Dist: Flask-SocketIO (>=0.5)
Requires-Dist: gunicorn (==18.0)
Requires-Dist: Pillow (>=2.7.0)
